joyful/__init__.py
joyful/finetune.py
joyful-0.0.1.dist-info/METADATA
joyful-0.0.1.dist-info/WHEEL
joyful-0.0.1.dist-info/licenses/LICENSE
joyful-0.0.1.dist-info/RECORD
